fennet_mhc/.DS_Store
fennet_mhc/__init__.py
fennet_mhc/cli.py
fennet_mhc/mhc_binding_model.py
fennet_mhc/mhc_binding_retriever.py
fennet_mhc/mhc_utils.py
fennet_mhc/pipeline_api.py
fennet_mhc/plotting_utils.py
fennet_mhc/tda_fmm.py
fennet_mhc/__pycache__/__init__.cpython-311.pyc
fennet_mhc/__pycache__/__init__.cpython-39.pyc
fennet_mhc/__pycache__/cli.cpython-311.pyc
fennet_mhc/__pycache__/cli.cpython-39.pyc
fennet_mhc/__pycache__/mhc_binding_model.cpython-311.pyc
fennet_mhc/__pycache__/mhc_binding_retriever.cpython-311.pyc
fennet_mhc/__pycache__/mhc_utils.cpython-311.pyc
fennet_mhc/__pycache__/pipeline_api.cpython-311.pyc
fennet_mhc/__pycache__/pipeline_api.cpython-39.pyc
fennet_mhc/__pycache__/tda_fmm.cpython-311.pyc
fennet_mhc/constants/__init__.py
fennet_mhc/constants/_const.py
fennet_mhc/constants/global_settings.yaml
fennet_mhc/constants/__pycache__/__init__.cpython-311.pyc
fennet_mhc/constants/__pycache__/_const.cpython-311.pyc
fennet_mhc-0.0.1.dev0.dist-info/LICENSE
fennet_mhc-0.0.1.dev0.dist-info/METADATA
fennet_mhc-0.0.1.dev0.dist-info/WHEEL
fennet_mhc-0.0.1.dev0.dist-info/entry_points.txt
fennet_mhc-0.0.1.dev0.dist-info/top_level.txt
fennet_mhc-0.0.1.dev0.dist-info/RECORD
