Metadata-Version: 2.1
Name: fennet-mhc
Version: 0.0.1.dev0
Summary: Fennet-MHC
Author-email: Wen-Feng Zeng <zengwenfeng@westlake.edu.cn>, Jin-Tao Cheng <1274873858@qq.com>
Maintainer-email: Wen-Feng Zeng <zengwenfeng@westlake.edu.cn>, Jin-Tao Cheng <1274873858@qq.com>
Project-URL: Homepage, https://fennomix.lab.westlake.edu.cn
Project-URL: Documentation, https://readthedocs.org
Project-URL: Repository, https://github.com/FennOmix/fennet.mhc.git
Project-URL: Bug Tracker, https://github.com/FennOmix/fennet.mhc/issues
Project-URL: Changelog, https://github.com/FennOmix/fennet.mhc/blob/main/CHANGELOG.md
Keywords: contrastive learning,protein language model,immunopeptidomics,mass spectrometry,HLA,MHC,peptide-MHC binding prediction
Classifier: Development Status :: 1 - Planning
Classifier: Programming Language :: Python
Requires-Python: <3.12,>=3.10
License-File: LICENSE
Provides-Extra: development
Provides-Extra: docs
Provides-Extra: stable
Provides-Extra: tests
